giig/__init__.py
giig/main.py
giigd-0.0.5.dist-info/METADATA
giigd-0.0.5.dist-info/WHEEL
giigd-0.0.5.dist-info/entry_points.txt
giigd-0.0.5.dist-info/top_level.txt
giigd-0.0.5.dist-info/RECORD
