Metadata-Version: 2.1
Name: giigd
Version: 0.0.5
Summary: gitignore cli
Home-page: https://github.com/ksundong/gitignore-cli-py
Author: Dion
Author-email: idion@idion.dev
License: UNKNOWN
Keywords: gitignore
Platform: UNKNOWN
Classifier: Programming Language :: Python :: 3
Classifier: License :: OSI Approved :: MIT License
Classifier: Operating System :: OS Independent
Requires-Python: >=3
Requires-Dist: click
Requires-Dist: fuzzywuzzy
Requires-Dist: python-Levenshtein
Requires-Dist: requests
